[
 {
   "id": 10004319,
   "uf": "SE",
   "cidade": "ARACAJU",
   "bairro": "SIQUEIRA CAMPOS",
   "endereco": "RUA PARAIBA, N. 443",
   "preco": "126.825,70",
   "valorAvaliacao": "216.500,00",
   "desconto": 41.42,
   "descricao": "Casa, 120.00 de área total, 80.50 de área privativa, 132.50 de área do terreno,  3 qto(s), varanda, WC, 1 sala(s), cozinha.",
   "modalidade": "Venda Direta Online",
   "link": "https://venda-imoveis.caixa.gov.br/sistema/detalhe-imovel.asp?hdnOrigem=index&hdnimovel=10004319"
 },
 {
   "id": 10007631,
   "uf": "SE",
   "cidade": "ARACAJU",
   "bairro": "JABOTIANA",
   "endereco": "RUA ANTONIO DORIA DA SILVA (ANTIGA RUA H), N. 72, QD 26",
   "preco": "235.143,60",
   "valorAvaliacao": "348.000,00",
   "desconto": 32.43,
   "descricao": "Casa, 0.00 de área total, 299.40 de área privativa, 208.00 de área do terreno,  4 qto(s), varanda, a.serv, WC, 3 sala(s), cozinha, Terraco, 1 vaga(s) de garagem.",
   "modalidade": "Venda Direta Online",
   "link": "https://venda-imoveis.caixa.gov.br/sistema/detalhe-imovel.asp?hdnOrigem=index&hdnimovel=10007631"
 },
 {
   "id": 10139933,
   "uf": "SE",
   "cidade": "ARACAJU",
   "bairro": "SAO JOSE",
   "endereco": "RUA DOM JOSE TOMAZ, N. 442, CASA",
   "preco": "614.655,75",
   "valorAvaliacao": "885.000,00",
   "desconto": 30.55,
   "descricao": "Casa, 0.00 de área total, 350.40 de área privativa, 0.00 de área do terreno, a.serv, 3 suite(s), WC, 3 sala(s), DCE, cozinha.",
   "modalidade": "Venda Direta Online",
   "link": "https://venda-imoveis.caixa.gov.br/sistema/detalhe-imovel.asp?hdnOrigem=index&hdnimovel=10139933"
 },
 {
   "id": 1444407313446,
   "uf": "SE",
   "cidade": "ARACAJU",
   "bairro": "ARUANA",
   "endereco": "RUA B, N. 23",
   "preco": "177.072,00",
   "valorAvaliacao": "240.000,00",
   "desconto": 26.22,
   "descricao": "Casa, 0.00 de área total, 65.20 de área privativa, 250.00 de área do terreno,  3 qto(s), a.serv, WC, 1 sala(s), cozinha.",
   "modalidade": "Licitação Aberta",
   "link": "https://venda-imoveis.caixa.gov.br/sistema/detalhe-imovel.asp?hdnOrigem=index&hdnimovel=1444407313446"
 },
 {
   "id": 1444413432370,
   "uf": "SE",
   "cidade": "ARACAJU",
   "bairro": "MATAPOA",
   "endereco": "RUA C, N. SN, LT 27, ZONA DE EXPANSAO",
   "preco": "292.906,60",
   "valorAvaliacao": "397.000,00",
   "desconto": 26.22,
   "descricao": "Terreno, 0.00 de área total, 0.00 de área privativa, 2091.00 de área do terreno.",
   "modalidade": "Licitação Aberta",
   "link": "https://venda-imoveis.caixa.gov.br/sistema/detalhe-imovel.asp?hdnOrigem=index&hdnimovel=1444413432370"
 },
 {
   "id": 240043120,
   "uf": "SE",
   "cidade": "ARACAJU",
   "bairro": "FAROLANDIA",
   "endereco": "RUA TENENTE WALDIR DOS SANTOS, N. 437, Apto 001, BLOCO 01 (RUA ANTONIO GUIMARAES)",
   "preco": "117.000,00",
   "valorAvaliacao": "117.000,00",
   "desconto": 0,
   "descricao": "Apartamento, 54.82 de área total, 49.26 de área privativa, 0.00 de área do terreno,  2 qto(s), a.serv, WC, 1 sala(s), cozinha, 1 vaga(s) de garagem.",
   "modalidade": "Venda Direta",
   "link": "https://venda-imoveis.caixa.gov.br/sistema/detalhe-imovel.asp?hdnOrigem=index&hdnimovel=240043120"
 },
 {
   "id": 240043138,
   "uf": "SE",
   "cidade": "ARACAJU",
   "bairro": "FAROLANDIA",
   "endereco": "AVENIDA MARIA PASTORA, N. 210, Apto 103, BLOCO 06",
   "preco": "100.000,00",
   "valorAvaliacao": "100.000,00",
   "desconto": 0,
   "descricao": "Apartamento, 52.97 de área total, 47.93 de área privativa, 0.00 de área do terreno,  2 qto(s), a.serv, WC, 1 sala(s), cozinha, 1 vaga(s) de garagem.",
   "modalidade": "Venda Direta",
   "link": "https://venda-imoveis.caixa.gov.br/sistema/detalhe-imovel.asp?hdnOrigem=index&hdnimovel=240043138"
 },
 {
   "id": 10148076,
   "uf": "SE",
   "cidade": "ARACAJU",
   "bairro": "NOVO PARAISO",
   "endereco": "RUA RIO GRANDE DO SUL, N. 548",
   "preco": "350.000,00",
   "valorAvaliacao": "350.000,00",
   "desconto": 0,
   "descricao": "Galpão, 0.00 de área total, 250.00 de área privativa, 277.14 de área do terreno.",
   "modalidade": "1º Leilão SFI",
   "link": "https://venda-imoveis.caixa.gov.br/sistema/detalhe-imovel.asp?hdnOrigem=index&hdnimovel=10148076"
 },
 {
   "id": 10148075,
   "uf": "SE",
   "cidade": "ARACAJU",
   "bairro": "SIQUEIRA CAMPOS",
   "endereco": "AVENIDA DESEMBARGADOR MAYNARD, N. S/N",
   "preco": "600.000,00",
   "valorAvaliacao": "600.000,00",
   "desconto": 0,
   "descricao": "Terreno, 0.00 de área total, 0.00 de área privativa, 378.00 de área do terreno.",
   "modalidade": "1º Leilão SFI",
   "link": "https://venda-imoveis.caixa.gov.br/sistema/detalhe-imovel.asp?hdnOrigem=index&hdnimovel=10148075"
 },
 {
   "id": 1444408438790,
   "uf": "SE",
   "cidade": "ARACAJU",
   "bairro": "GRAGERU",
   "endereco": "A HERMES FONTES, N. 1620, Apto 1620, 201, E",
   "preco": "231.900,00",
   "valorAvaliacao": "220.000,00",
   "desconto": 0,
   "descricao": "Apartamento, 83.98 de área total, 77.70 de área privativa, 0.00 de área do terreno,  3 qto(s), a.serv, WC, WC Emp, 1 sala(s), cozinha.",
   "modalidade": "1º Leilão SFI",
   "link": "https://venda-imoveis.caixa.gov.br/sistema/detalhe-imovel.asp?hdnOrigem=index&hdnimovel=1444408438790"
 },
 {
   "id": 1444407855028,
   "uf": "SE",
   "cidade": "ARACAJU",
   "bairro": "GRAGERU",
   "endereco": "AVENIDA SILVIO TEIXEIRA, N. 1333, Apto 204, BL B",
   "preco": "465.100,00",
   "valorAvaliacao": "390.000,00",
   "desconto": 0,
   "descricao": "Apartamento, 0.00 de área total, 99.79 de área privativa, 0.00 de área do terreno,  3 qto(s), a.serv, WC, 1 sala(s), DCE, cozinha, 1 vaga(s) de garagem.",
   "modalidade": "1º Leilão SFI",
   "link": "https://venda-imoveis.caixa.gov.br/sistema/detalhe-imovel.asp?hdnOrigem=index&hdnimovel=1444407855028"
 },
 {
   "id": 8555510791550,
   "uf": "SE",
   "cidade": "ARACAJU",
   "bairro": "FAROLANDIA",
   "endereco": "R LENIO DE MOURA MORAIS (ANTIGA RUA E-1), N. 255, Apto 303, Bloco 4.",
   "preco": "132.000,00",
   "valorAvaliacao": "107.000,00",
   "desconto": 0,
   "descricao": "Apartamento, 0.00 de área total, 59.68 de área privativa, 0.00 de área do terreno,  3 qto(s), a.serv, WC, 1 sala(s), cozinha.",
   "modalidade": "1º Leilão SFI",
   "link": "https://venda-imoveis.caixa.gov.br/sistema/detalhe-imovel.asp?hdnOrigem=index&hdnimovel=8555510791550"
 },
 {
   "id": 1787700040523,
   "uf": "SE",
   "cidade": "BARRA DOS COQUEIROS",
   "bairro": "CENTRO",
   "endereco": "AVENIDA OCEANICA, N. 800, Apto 305, BL 02, BLOCO PRAIA DO PORTO, GARAGEM 7",
   "preco": "143.400,00",
   "valorAvaliacao": "125.000,00",
   "desconto": 0,
   "descricao": "Apartamento, 0.00 de área total, 51.02 de área privativa, 0.00 de área do terreno,  3 qto(s), varanda, a.serv, WC, 1 sala(s), cozinha, 1 vaga(s) de garagem.",
   "modalidade": "1º Leilão SFI",
   "link": "https://venda-imoveis.caixa.gov.br/sistema/detalhe-imovel.asp?hdnOrigem=index&hdnimovel=1787700040523"
 },
 {
   "id": 8555531381571,
   "uf": "SE",
   "cidade": "BARRA DOS COQUEIROS",
   "bairro": "POVOADO CAPOA",
   "endereco": "AVENIDA PROJETADA ALAMEDAS DA BARRA, N. 410, Apto 006, BL 10",
   "preco": "132.900,00",
   "valorAvaliacao": "100.000,00",
   "desconto": 0,
   "descricao": "Apartamento, 71.42 de área total, 58.79 de área privativa, 0.00 de área do terreno,  3 qto(s), a.serv, WC, cozinha, 1 vaga(s) de garagem.",
   "modalidade": "1º Leilão SFI",
   "link": "https://venda-imoveis.caixa.gov.br/sistema/detalhe-imovel.asp?hdnOrigem=index&hdnimovel=8555531381571"
 },
 {
   "id": 1555532463743,
   "uf": "SE",
   "cidade": "BARRA DOS COQUEIROS",
   "bairro": "POVOADO CAPOA",
   "endereco": "AVENIDA PROJETADA, N. 410, Apto 306, BL 04, ALAMEDAS DA BARRA",
   "preco": "267.200,00",
   "valorAvaliacao": "130.000,00",
   "desconto": 0,
   "descricao": "Apartamento, 0.00 de área total, 58.79 de área privativa, 0.00 de área do terreno,  3 qto(s), varanda, WC, 1 sala(s), cozinha.",
   "modalidade": "2º Leilão SFI",
   "link": "https://venda-imoveis.caixa.gov.br/sistema/detalhe-imovel.asp?hdnOrigem=index&hdnimovel=1555532463743"
 },
 {
   "id": 8444411289390,
   "uf": "SE",
   "cidade": "CAPELA",
   "bairro": "BAIRRO AEROPORTO",
   "endereco": "RUA PROJETADA A, N. 254, QD A LT 44",
   "preco": "29.876,00",
   "valorAvaliacao": "70.000,00",
   "desconto": 57.32,
   "descricao": "Casa, 0.00 de área total, 69.85 de área privativa, 92.48 de área do terreno,  3 qto(s), WC, 1 sala(s), cozinha.",
   "modalidade": "Venda Direta Online",
   "link": "https://venda-imoveis.caixa.gov.br/sistema/detalhe-imovel.asp?hdnOrigem=index&hdnimovel=8444411289390"
 },
 {
   "id": 8444409592294,
   "uf": "SE",
   "cidade": "CAPELA",
   "bairro": "CENTRO",
   "endereco": "RUA PROJETADA A, N. 230, ANTIGA QD.A, LT.40",
   "preco": "14.999,60",
   "valorAvaliacao": "28.000,00",
   "desconto": 46.43,
   "descricao": "Casa, 0.00 de área total, 69.82 de área privativa, 92.48 de área do terreno,  3 qto(s), WC, 1 sala(s), cozinha, 1 vaga(s) de garagem.",
   "modalidade": "Venda Direta Online",
   "link": "https://venda-imoveis.caixa.gov.br/sistema/detalhe-imovel.asp?hdnOrigem=index&hdnimovel=8444409592294"
 },
 {
   "id": 8444404756043,
   "uf": "SE",
   "cidade": "CAPELA",
   "bairro": "CENTRO",
   "endereco": "Rua Projetada Quadra C Lote 14, N. 14",
   "preco": "51.085,49",
   "valorAvaliacao": "56.250,00",
   "desconto": 9.19,
   "descricao": "Casa, 69.96 de área total, 69.96 de área privativa, 84.00 de área do terreno,  2 qto(s), WC, 1 sala(s), cozinha, 1 vaga(s) de garagem.",
   "modalidade": "Venda Direta Online",
   "link": "https://venda-imoveis.caixa.gov.br/sistema/detalhe-imovel.asp?hdnOrigem=index&hdnimovel=8444404756043"
 },
 {
   "id": 8444408901870,
   "uf": "SE",
   "cidade": "CAPELA",
   "bairro": "SOBRADINHO",
   "endereco": "RUA PROJETADA B, N. 26, LT 08",
   "preco": "131.200,00",
   "valorAvaliacao": "120.000,00",
   "desconto": 0,
   "descricao": "Casa, 0.00 de área total, 69.60 de área privativa, 114.00 de área do terreno,  2 qto(s), a.serv, WC, 1 sala(s), cozinha, 1 vaga(s) de garagem.",
   "modalidade": "1º Leilão SFI",
   "link": "https://venda-imoveis.caixa.gov.br/sistema/detalhe-imovel.asp?hdnOrigem=index&hdnimovel=8444408901870"
 },
 {
   "id": 8444409295141,
   "uf": "SE",
   "cidade": "CAPELA",
   "bairro": "SOBRADINHO",
   "endereco": "RUA PROJETADA B, N. 20",
   "preco": "149.400,00",
   "valorAvaliacao": "102.000,00",
   "desconto": 0,
   "descricao": "Casa, 0.00 de área total, 69.60 de área privativa, 114.00 de área do terreno,  2 qto(s), WC, 1 sala(s), cozinha, 1 vaga(s) de garagem.",
   "modalidade": "2º Leilão SFI",
   "link": "https://venda-imoveis.caixa.gov.br/sistema/detalhe-imovel.asp?hdnOrigem=index&hdnimovel=8444409295141"
 },
 {
   "id": 8444413478042,
   "uf": "SE",
   "cidade": "CAPELA",
   "bairro": "CAPELA",
   "endereco": "RUA PROJETADA A, N. 81, QDB, LT11",
   "preco": "132.300,00",
   "valorAvaliacao": "90.000,00",
   "desconto": 0,
   "descricao": "Casa, 0.00 de área total, 69.90 de área privativa, 78.00 de área do terreno,  3 qto(s), a.serv, WC, 1 sala(s), cozinha, 1 vaga(s) de garagem.",
   "modalidade": "2º Leilão SFI",
   "link": "https://venda-imoveis.caixa.gov.br/sistema/detalhe-imovel.asp?hdnOrigem=index&hdnimovel=8444413478042"
 },
 {
   "id": 8444405151536,
   "uf": "SE",
   "cidade": "CAPELA",
   "bairro": "SOBRADINHO",
   "endereco": "RUA PROJETADA F, N. 337, LOTE 02",
   "preco": "145.700,00",
   "valorAvaliacao": "98.000,00",
   "desconto": 0,
   "descricao": "Casa, 0.00 de área total, 74.61 de área privativa, 108.00 de área do terreno,  2 qto(s), a.serv, WC, 1 sala(s), cozinha, 1 vaga(s) de garagem.",
   "modalidade": "1º Leilão SFI",
   "link": "https://venda-imoveis.caixa.gov.br/sistema/detalhe-imovel.asp?hdnOrigem=index&hdnimovel=8444405151536"
 },
 {
   "id": 8444410451623,
   "uf": "SE",
   "cidade": "CAPELA",
   "bairro": "SOBRADINHO",
   "endereco": "RUA PROJETADA C, N. 03, LT 01, QD C",
   "preco": "124.000,00",
   "valorAvaliacao": "68.000,00",
   "desconto": 0,
   "descricao": "Casa, 0.00 de área total, 69.60 de área privativa, 85.20 de área do terreno,  2 qto(s), WC, 1 sala(s), cozinha, 1 vaga(s) de garagem.",
   "modalidade": "1º Leilão SFI",
   "link": "https://venda-imoveis.caixa.gov.br/sistema/detalhe-imovel.asp?hdnOrigem=index&hdnimovel=8444410451623"
 },
 {
   "id": 1555528724406,
   "uf": "SE",
   "cidade": "ESTANCIA",
   "bairro": "CENTRO",
   "endereco": "RUA ANTONIO COSTA CARVALHO, N. 503, ANT TRAVESSA VISCONDE DE INHAUMA",
   "preco": "150.000,00",
   "valorAvaliacao": "150.000,00",
   "desconto": 0,
   "descricao": "Casa, 0.00 de área total, 147.10 de área privativa, 346.50 de área do terreno,  3 qto(s), a.serv, WC, 2 sala(s), cozinha, 1 vaga(s) de garagem.",
   "modalidade": "1º Leilão SFI",
   "link": "https://venda-imoveis.caixa.gov.br/sistema/detalhe-imovel.asp?hdnOrigem=index&hdnimovel=1555528724406"
 },
 {
   "id": 8444411587910,
   "uf": "SE",
   "cidade": "ESTANCIA",
   "bairro": "BOTEQUIM",
   "endereco": "RUA F, N. 61, QD E, LT 24, LOT COSTA VERDE",
   "preco": "114.700,00",
   "valorAvaliacao": "105.000,00",
   "desconto": 0,
   "descricao": "Casa, 0.00 de área total, 54.65 de área privativa, 160.00 de área do terreno,  2 qto(s), a.serv, WC, 1 sala(s), cozinha.",
   "modalidade": "1º Leilão SFI",
   "link": "https://venda-imoveis.caixa.gov.br/sistema/detalhe-imovel.asp?hdnOrigem=index&hdnimovel=8444411587910"
 },
 {
   "id": 10152092,
   "uf": "SE",
   "cidade": "ESTANCIA",
   "bairro": "ESTANCIA",
   "endereco": "ESTRADA DE SALGADO, ZONA RURAL",
   "preco": "850.000,00",
   "valorAvaliacao": "750.000,00",
   "desconto": 0,
   "descricao": "Terreno, 0.00 de área total, 0.00 de área privativa, 2084.13 de área do terreno.",
   "modalidade": "1º Leilão SFI",
   "link": "https://venda-imoveis.caixa.gov.br/sistema/detalhe-imovel.asp?hdnOrigem=index&hdnimovel=10152092"
 },
 {
   "id": 8444413628389,
   "uf": "SE",
   "cidade": "ITABAIANA",
   "bairro": "DOUTOR JOSE MILTON MACHADO",
   "endereco": "RUA FOGO PAGOU, N. 52, QD C, LT 35",
   "preco": "75.000,00",
   "valorAvaliacao": "125.000,00",
   "desconto": 40,
   "descricao": "Casa, 0.00 de área total, 110.07 de área privativa, 138.00 de área do terreno,  3 qto(s), a.serv, WC, 1 sala(s), cozinha, 1 vaga(s) de garagem.",
   "modalidade": "Licitação Aberta",
   "link": "https://venda-imoveis.caixa.gov.br/sistema/detalhe-imovel.asp?hdnOrigem=index&hdnimovel=8444413628389"
 },
 {
   "id": 1444406044778,
   "uf": "SE",
   "cidade": "ITABAIANA",
   "bairro": "OVIEDO TEIXEIRA",
   "endereco": "RUA ARMANDO PAES DA COSTA, N. 730, QD L, LT 34",
   "preco": "93.669,99",
   "valorAvaliacao": "145.000,00",
   "desconto": 35.41,
   "descricao": "Casa, 0.00 de área total, 120.90 de área privativa, 160.00 de área do terreno,  3 qto(s), varanda, a.serv, WC, 1 sala(s), cozinha.",
   "modalidade": "Licitação Aberta",
   "link": "https://venda-imoveis.caixa.gov.br/sistema/detalhe-imovel.asp?hdnOrigem=index&hdnimovel=1444406044778"
 },
 {
   "id": 10147859,
   "uf": "SE",
   "cidade": "ITABAIANA",
   "bairro": "PORTO",
   "endereco": "AVENIDA EDUARDO PAIXAO ROCHA, N. S/N, TERRENO 2",
   "preco": "1.523.970,00",
   "valorAvaliacao": "2.100.000,00",
   "desconto": 27.43,
   "descricao": "Terreno, 0.00 de área total, 0.00 de área privativa, 7901.99 de área do terreno.",
   "modalidade": "Licitação Aberta",
   "link": "https://venda-imoveis.caixa.gov.br/sistema/detalhe-imovel.asp?hdnOrigem=index&hdnimovel=10147859"
 },
 {
   "id": 10152799,
   "uf": "SE",
   "cidade": "ITABAIANA",
   "bairro": "ITABAIANA",
   "endereco": "AREA RURAL, SÍTIO QUEIMADINHAS",
   "preco": "1.850.000,00",
   "valorAvaliacao": "1.850.000,00",
   "desconto": 0,
   "descricao": "Imóvel rural, 0.00 de área total, 0.00 de área privativa, 60500.00 de área do terreno.",
   "modalidade": "1º Leilão SFI",
   "link": "https://venda-imoveis.caixa.gov.br/sistema/detalhe-imovel.asp?hdnOrigem=index&hdnimovel=10152799"
 },
 {
   "id": 1444400678392,
   "uf": "SE",
   "cidade": "ITABAIANA",
   "bairro": "SAO CRISTOVAO",
   "endereco": "TRAVESSA ANTONIO SALES DO NASCIMENTO, N. 181, QUADRA D, CASA 01",
   "preco": "125.000,00",
   "valorAvaliacao": "125.000,00",
   "desconto": 0,
   "descricao": "Casa, 79.27 de área total, 79.27 de área privativa, 83.73 de área do terreno,  2 qto(s), a.serv, WC, 1 sala(s), cozinha, 1 vaga(s) de garagem.",
   "modalidade": "1º Leilão SFI",
   "link": "https://venda-imoveis.caixa.gov.br/sistema/detalhe-imovel.asp?hdnOrigem=index&hdnimovel=1444400678392"
 },
 {
   "id": 8444408663287,
   "uf": "SE",
   "cidade": "ITABAIANA",
   "bairro": "MAMEDE PAES MENDONCA",
   "endereco": "RUA PROFESSOR LIMA JUNIOR, N. 1596",
   "preco": "125.000,00",
   "valorAvaliacao": "125.000,00",
   "desconto": 0,
   "descricao": "Casa, 0.00 de área total, 101.37 de área privativa, 134.91 de área do terreno,  3 qto(s), a.serv, WC, 1 sala(s), cozinha, 1 vaga(s) de garagem.",
   "modalidade": "1º Leilão SFI",
   "link": "https://venda-imoveis.caixa.gov.br/sistema/detalhe-imovel.asp?hdnOrigem=index&hdnimovel=8444408663287"
 },
 {
   "id": 8444421370875,
   "uf": "SE",
   "cidade": "ITABAIANA",
   "bairro": "DOUTOR JOSE MILTON MACHADO",
   "endereco": "RUA BAIAO DE DOIS, N. 254, QDR2, L24",
   "preco": "131.700,00",
   "valorAvaliacao": "125.000,00",
   "desconto": 0,
   "descricao": "Casa, 0.00 de área total, 97.81 de área privativa, 130.00 de área do terreno,  3 qto(s), a.serv, WC, 1 sala(s), cozinha, 1 vaga(s) de garagem.",
   "modalidade": "1º Leilão SFI",
   "link": "https://venda-imoveis.caixa.gov.br/sistema/detalhe-imovel.asp?hdnOrigem=index&hdnimovel=8444421370875"
 },
 {
   "id": 10152800,
   "uf": "SE",
   "cidade": "ITABAIANA",
   "bairro": "ITABAIANA",
   "endereco": "AREA RURAL, SITIO QUEIMADINHAS",
   "preco": "815.700,00",
   "valorAvaliacao": "760.000,00",
   "desconto": 0,
   "descricao": "Imóvel rural, 0.00 de área total, 0.00 de área privativa, 21175.00 de área do terreno.",
   "modalidade": "1º Leilão SFI",
   "link": "https://venda-imoveis.caixa.gov.br/sistema/detalhe-imovel.asp?hdnOrigem=index&hdnimovel=10152800"
 },
 {
   "id": 8444403578591,
   "uf": "SE",
   "cidade": "ITABAIANA",
   "bairro": "PORTO",
   "endereco": "RUA PROJETADA D, N. 53, D04LOTEAMENTO JARDIM UNIVERSITÁRIO",
   "preco": "112.400,00",
   "valorAvaliacao": "71.000,00",
   "desconto": 0,
   "descricao": "Casa, 66.71 de área total, 66.71 de área privativa, 130.50 de área do terreno,  3 qto(s), a.serv, WC, 1 sala(s), 1 vaga(s) de garagem.",
   "modalidade": "1º Leilão SFI",
   "link": "https://venda-imoveis.caixa.gov.br/sistema/detalhe-imovel.asp?hdnOrigem=index&hdnimovel=8444403578591"
 },
 {
   "id": 1444402343410,
   "uf": "SE",
   "cidade": "ITABAIANINHA",
   "bairro": "CENTRO",
   "endereco": "RUA JOSE PRIMO, N. 20, QD 02, LT 21",
   "preco": "154.000,00",
   "valorAvaliacao": "154.000,00",
   "desconto": 0,
   "descricao": "Casa, 80.00 de área total, 80.00 de área privativa, 115.50 de área do terreno,  3 qto(s), a.serv, WC, 1 sala(s), cozinha, 1 vaga(s) de garagem.",
   "modalidade": "1º Leilão SFI",
   "link": "https://venda-imoveis.caixa.gov.br/sistema/detalhe-imovel.asp?hdnOrigem=index&hdnimovel=1444402343410"
 },
 {
   "id": 1444405048346,
   "uf": "SE",
   "cidade": "NEOPOLIS",
   "bairro": "CENTRO",
   "endereco": "AVENIDA SOLON GUEDES BARRETO, N. 557",
   "preco": "235.200,00",
   "valorAvaliacao": "60.000,00",
   "desconto": 0,
   "descricao": "Casa, 152.00 de área total, 152.00 de área privativa, 512.00 de área do terreno,  3 qto(s), a.serv, WC, 3 sala(s), cozinha.",
   "modalidade": "1º Leilão SFI",
   "link": "https://venda-imoveis.caixa.gov.br/sistema/detalhe-imovel.asp?hdnOrigem=index&hdnimovel=1444405048346"
 },
 {
   "id": 10007919,
   "uf": "SE",
   "cidade": "NOSSA SENHORA DO SOCORRO",
   "bairro": "CENTRO HISTORICO",
   "endereco": "AVENIDA G, QD 21 LT 09/10/11/12A",
   "preco": "1.268.257,00",
   "valorAvaliacao": "2.165.000,00",
   "desconto": 41.42,
   "descricao": "Comercial, 2100.00 de área total, 2100.00 de área privativa, 13125.00 de área do terreno.",
   "modalidade": "Venda Direta Online",
   "link": "https://venda-imoveis.caixa.gov.br/sistema/detalhe-imovel.asp?hdnOrigem=index&hdnimovel=10007919"
 },
 {
   "id": 8444421988755,
   "uf": "SE",
   "cidade": "NOSSA SENHORA DO SOCORRO",
   "bairro": "COMPLEXO JARDIM",
   "endereco": "RUA M, N. 132, QD20, LT36A",
   "preco": "105.000,00",
   "valorAvaliacao": "105.000,00",
   "desconto": 0,
   "descricao": "Casa, 0.00 de área total, 67.50 de área privativa, 125.00 de área do terreno,  2 qto(s), a.serv, WC, 1 sala(s), cozinha.",
   "modalidade": "1º Leilão SFI",
   "link": "https://venda-imoveis.caixa.gov.br/sistema/detalhe-imovel.asp?hdnOrigem=index&hdnimovel=8444421988755"
 },
 {
   "id": 8555518089005,
   "uf": "SE",
   "cidade": "NOSSA SENHORA DO SOCORRO",
   "bairro": "CONJ JARDIM II",
   "endereco": "RUA C, N. 06, QD 03, LT 03, CONJUNTO JARDIM II",
   "preco": "135.000,00",
   "valorAvaliacao": "135.000,00",
   "desconto": 0,
   "descricao": "Casa, 0.00 de área total, 68.80 de área privativa, 105.00 de área do terreno,  2 qto(s), a.serv, WC, 1 sala(s), cozinha.",
   "modalidade": "1º Leilão SFI",
   "link": "https://venda-imoveis.caixa.gov.br/sistema/detalhe-imovel.asp?hdnOrigem=index&hdnimovel=8555518089005"
 },
 {
   "id": 10145476,
   "uf": "SE",
   "cidade": "POCO VERDE",
   "bairro": "poço verde",
   "endereco": "RODOVIA SE 110, N. S/N, PERIMETRO URBANO",
   "preco": "667.644,00",
   "valorAvaliacao": "920.000,00",
   "desconto": 27.43,
   "descricao": "Terreno, 0.00 de área total, 0.00 de área privativa, 17000.00 de área do terreno.",
   "modalidade": "Venda Direta Online",
   "link": "https://venda-imoveis.caixa.gov.br/sistema/detalhe-imovel.asp?hdnOrigem=index&hdnimovel=10145476"
 },
 {
   "id": 1444406311849,
   "uf": "SE",
   "cidade": "POCO VERDE",
   "bairro": "BOA ESPERANCA",
   "endereco": "RODOVIA ESTADUAL SE-218, N. S/N, RUA H, LT 11, QD 06",
   "preco": "73.000,00",
   "valorAvaliacao": "73.000,00",
   "desconto": 0,
   "descricao": "Casa, 0.00 de área total, 42.97 de área privativa, 144.00 de área do terreno,  3 qto(s), a.serv, WC, 1 sala(s), cozinha.",
   "modalidade": "1º Leilão SFI",
   "link": "https://venda-imoveis.caixa.gov.br/sistema/detalhe-imovel.asp?hdnOrigem=index&hdnimovel=1444406311849"
 },
 {
   "id": 10006844,
   "uf": "SE",
   "cidade": "SALGADO",
   "bairro": "CENTRO",
   "endereco": "Estrada Real - Sítio Sales. Estrada do Pov Cabral, N. S/N, Sítio Presépio",
   "preco": "118.917,40",
   "valorAvaliacao": "203.000,00",
   "desconto": 41.42,
   "descricao": "Imóvel rural, 0.00 de área total, 0.00 de área privativa, 64713.00 de área do terreno.",
   "modalidade": "Venda Direta Online",
   "link": "https://venda-imoveis.caixa.gov.br/sistema/detalhe-imovel.asp?hdnOrigem=index&hdnimovel=10006844"
 },
 {
   "id": 8444408785986,
   "uf": "SE",
   "cidade": "SAO CRISTOVAO",
   "bairro": "ROSA ELZE",
   "endereco": "RODOVIA JOAO BEBE AGUA (ANTIGA RUA PROJETADA), N. 189, Apto 202, BL 03",
   "preco": "62.336,99",
   "valorAvaliacao": "110.000,00",
   "desconto": 43.34,
   "descricao": "Apartamento, 0.00 de área total, 43.13 de área privativa, 0.00 de área do terreno,  2 qto(s), a.serv, WC, 1 sala(s), 1 lavabo(s), cozinha.",
   "modalidade": "Licitação Aberta",
   "link": "https://venda-imoveis.caixa.gov.br/sistema/detalhe-imovel.asp?hdnOrigem=index&hdnimovel=8444408785986"
 },
 {
   "id": 1555525366444,
   "uf": "SE",
   "cidade": "SAO CRISTOVAO",
   "bairro": "VARZEA GRANDE",
   "endereco": "ESTRADA DA VÁRZEA GRANDE, N. 103, Apto 303, BL02",
   "preco": "177.600,00",
   "valorAvaliacao": "210.000,00",
   "desconto": 15.43,
   "descricao": "Apartamento, 0.00 de área total, 63.31 de área privativa, 0.00 de área do terreno,  3 qto(s), varanda, a.serv, WC, 1 sala(s), cozinha.",
   "modalidade": "2º Leilão SFI",
   "link": "https://venda-imoveis.caixa.gov.br/sistema/detalhe-imovel.asp?hdnOrigem=index&hdnimovel=1555525366444"
 },
 {
   "id": 1444403779190,
   "uf": "SE",
   "cidade": "TOBIAS BARRETO",
   "bairro": "CENTRO",
   "endereco": "RUA ANTONIO ALVES DE OLIVEIRA (ANTIGA RUA 40), N. S/N, QD 44 - LT 28",
   "preco": "1.875,20",
   "valorAvaliacao": "32.000,00",
   "desconto": 94.14,
   "descricao": "Terreno, 0.00 de área total, 0.00 de área privativa, 143.50 de área do terreno.",
   "modalidade": "Licitação Aberta",
   "link": "https://venda-imoveis.caixa.gov.br/sistema/detalhe-imovel.asp?hdnOrigem=index&hdnimovel=1444403779190"
 },
 {
   "id": 1444403689476,
   "uf": "SE",
   "cidade": "TOBIAS BARRETO",
   "bairro": "BAIRRO MACAÉ",
   "endereco": "RUA ANTONIO ALVES DE OLIVEIRA (TONHO DE ASTÉRIO), N. S/N, RUA 40, QD 45, LT 35",
   "preco": "65.245,99",
   "valorAvaliacao": "101.000,00",
   "desconto": 35.41,
   "descricao": "Casa, 0.00 de área total, 58.34 de área privativa, 143.50 de área do terreno,  2 qto(s), varanda, a.serv, WC, 1 sala(s), cozinha.",
   "modalidade": "Licitação Aberta",
   "link": "https://venda-imoveis.caixa.gov.br/sistema/detalhe-imovel.asp?hdnOrigem=index&hdnimovel=1444403689476"
 },
 {
   "id": 1555533704671,
   "uf": "SE",
   "cidade": "TOMAR DO GERU",
   "bairro": "CENTRO",
   "endereco": "RUA 08 DE SETEMBRO, N. 213",
   "preco": "144.404,00",
   "valorAvaliacao": "260.000,00",
   "desconto": 44.46,
   "descricao": "Casa, 0.00 de área total, 414.14 de área privativa, 206.04 de área do terreno,  3 qto(s), varanda, a.serv, WC, 4 sala(s), cozinha.",
   "modalidade": "Licitação Aberta",
   "link": "https://venda-imoveis.caixa.gov.br/sistema/detalhe-imovel.asp?hdnOrigem=index&hdnimovel=1555533704671"
 }
]